gtfs_canonical_validator/__init__.py
gtfs_canonical_validator/constants.py
gtfs_canonical_validator/gtfs_validator.py
gtfs_canonical_validator/version.py
gtfs_canonical_validator/models/__init__.py
gtfs_canonical_validator/models/response.py
gtfs_canonical_validator-0.0.8.dist-info/LICENSE
gtfs_canonical_validator-0.0.8.dist-info/METADATA
gtfs_canonical_validator-0.0.8.dist-info/WHEEL
gtfs_canonical_validator-0.0.8.dist-info/top_level.txt
gtfs_canonical_validator-0.0.8.dist-info/RECORD
