Metadata-Version: 2.1
Name: gtfs-canonical-validator
Version: 0.0.8
Summary: Package is used for validate the canonical data.
Home-page: https://github.com/TaskarCenterAtUW/TDEI-mobilitydata-canonical-validator
Author: Sujata Misra
Author-email: sujatam@gaussiansolutions.com
Project-URL: Documentation, https://github.com/TaskarCenterAtUW/TDEI-mobilitydata-canonical-validator/blob/main/README.md
Project-URL: GitHub, https://github.com/TaskarCenterAtUW/TDEI-mobilitydata-canonical-validator
Project-URL: Changelog, https://github.com/TaskarCenterAtUW/TDEI-mobilitydata-canonical-validator/blob/main/CHANGELOG.md
Classifier: Programming Language :: Python :: 3
Classifier: License :: OSI Approved :: MIT License
Classifier: Operating System :: OS Independent
Requires-Python: >=3.10
License-File: LICENSE
Requires-Dist: requests
